other/__init__.py
other/before_test.py
other/common/__init__.py
other/common/database/__init__.py
other/common/database/user/__init__.py
other/common/database/user/main.py
other/common/database/variable/__init__.py
other/common/database/variable/storage.py
other/common/database/variable/ucode_student_user_token.py
other/common/file/__init__.py
other/common/file/io.py
other/common/file/list.py
other/etl/__init__.py
other/etl/problem/__init__.py
other/etl/problem/1000_c_problem/__init__.py
other/etl/problem/1000_c_problem/main.py
other/etl/user/__init__.py
other/etl/user/vio/__init__.py
other/etl/user/vio/main.py
other/etl/user/vio/model.py
other/testing/__init__.py
other/testing/performance_testing/__init__.py
other/testing/performance_testing/contest/__init__.py
other/testing/performance_testing/contest/main.py
other/testing/performance_testing/contest/test_script.py
other/testing/performance_testing/contest/user_data_draff.py
ucode/__init__.py
ucode/api/__init__.py
ucode/cli/__init__.py
ucode/cli/cf_command.py
ucode/cli/dsa_command.py
ucode/cli/main.py
ucode/cli/ucode_command.py
ucode/cli_/__init__.py
ucode/cli_/ucode_cli.py
ucode/gui/__init__.py
ucode/gui/gui.py
ucode/helpers/__init__.py
ucode/helpers/clog.py
ucode/helpers/config.py
ucode/helpers/crandom.py
ucode/helpers/misc.py
ucode/helpers/shell_helper.py
ucode/models/__init__.py
ucode/models/lesson.py
ucode/models/problem.py
ucode/models/question.py
ucode/oj/__init__.py
ucode/oj/codeforces/__init__.py
ucode/oj/codeforces/aes.py
ucode/oj/codeforces/codeforces.py
ucode/oj/codeforces/codeforces_helper.py
ucode/oj/free_contest/__init__.py
ucode/oj/free_contest/free_contest.py
ucode/oj/gform/__init__.py
ucode/oj/gform/gform.py
ucode/oj/judge0/__init__.py
ucode/oj/judge0/judge0.py
ucode/services/__init__.py
ucode/services/common.py
ucode/services/dsa/__init__.py
ucode/services/dsa/problem_service.py
ucode/services/dsa/question_service.py
ucode/services/dsa/templates/editorial.md
ucode_cli-2.5.5.dist-info/LICENSE.txt
ucode_cli-2.5.5.dist-info/METADATA
ucode_cli-2.5.5.dist-info/WHEEL
ucode_cli-2.5.5.dist-info/entry_points.txt
ucode_cli-2.5.5.dist-info/top_level.txt
ucode_cli-2.5.5.dist-info/RECORD
