Metadata-Version: 2.1
Name: ucode-cli
Version: 2.5.5
Summary: CLI tools to prepare problems locally and to work with ucode.vn server
Home-page: https://gitlab.com/ucodevn/ucode-cli
Author: Thuc Nguyen
Author-email: gthuc.nguyen@gmail.com
License: MIT
Download-URL: https://pypi.org/project/ucode/
Keywords: ucode,ucode CLI tools
Platform: UNKNOWN
License-File: LICENSE.txt
Requires-Dist: click
Requires-Dist: requests
Requires-Dist: beautifulsoup4
Requires-Dist: tomd
Requires-Dist: jinja2
Requires-Dist: dataclasses-json
Requires-Dist: unidecode
Requires-Dist: typer
Requires-Dist: colorama
Requires-Dist: ruamel.yaml
Requires-Dist: pysimplegui
